setup.py
dst_probdistribution/Binomialdistribution.py
dst_probdistribution/Gaussiandistribution.py
dst_probdistribution/Generaldistribution.py
dst_probdistribution/__init__.py
dst_probdistribution.egg-info/PKG-INFO
dst_probdistribution.egg-info/SOURCES.txt
dst_probdistribution.egg-info/dependency_links.txt
dst_probdistribution.egg-info/not-zip-safe
dst_probdistribution.egg-info/top_level.txt