Metadata-Version: 1.0
Name: dst-probdistribution
Version: 0.1
Summary: Gaussian & Binomial distributions
Home-page: UNKNOWN
Author: Hillary
Author-email: hillarywang2005@gmail.com
License: UNKNOWN
Platform: UNKNOWN
